bigeye_cli/CLI_DOCS.md
bigeye_cli/__init__.py
bigeye_cli/__main__.py
bigeye_cli/__version__.py
bigeye_cli/bigconfig/__init__.py
bigeye_cli/bigconfig/bigconfig_commands.py
bigeye_cli/bigconfig/bigconfig_options.py
bigeye_cli/catalog/__init__.py
bigeye_cli/catalog/catalog_commands.py
bigeye_cli/collections/__init__.py
bigeye_cli/collections/collection_commands.py
bigeye_cli/configure/__init__.py
bigeye_cli/configure/configure_commands.py
bigeye_cli/deltas/__init__.py
bigeye_cli/deltas/deltas_commands.py
bigeye_cli/enums.py
bigeye_cli/exceptions/__init__.py
bigeye_cli/exceptions/exceptions.py
bigeye_cli/functions.py
bigeye_cli/global_options.py
bigeye_cli/issues/__init__.py
bigeye_cli/issues/issue_commands.py
bigeye_cli/lineage/__init__.py
bigeye_cli/lineage/lineage_commands.py
bigeye_cli/metric/__init__.py
bigeye_cli/metric/metric_commands.py
bigeye_cli/model/__init__.py
bigeye_cli/model/cicd_conf.py
bigeye_cli/model/github_report.py
bigeye_cli/model/vendor_report.py
bigeye_cli/workspace/__init__.py
bigeye_cli/workspace/workspace_commands.py
bigeye_cli-0.7.2.dist-info/LICENSE
bigeye_cli-0.7.2.dist-info/METADATA
bigeye_cli-0.7.2.dist-info/WHEEL
bigeye_cli-0.7.2.dist-info/entry_points.txt
bigeye_cli-0.7.2.dist-info/RECORD
