Metadata-Version: 2.1
Name: bigeye-cli
Version: 0.7.2
Summary: Bigeye CLI offers developer tools for maintaining your developer workspace.
Home-page: https://docs.bigeye.com/docs
License: Proprietary
Author: Bigeye
Author-email: support@bigeye.com
Requires-Python: >=3.11.0,<4.0.0
Classifier: License :: Other/Proprietary License
Classifier: Programming Language :: Python :: 3
Classifier: Programming Language :: Python :: 3.11
Classifier: Programming Language :: Python :: 3.12
Requires-Dist: PyGithub (>=1.59.1,<2.0.0)
Requires-Dist: bigeye-sdk (>=0.8.0,<0.9.0)
Requires-Dist: click (>=8.1.8,<9.0.0)
Requires-Dist: rich (>=14.1.0,<15.0.0)
